carpisettings/__init__.py
carpi_settings-0.1.2.dist-info/LICENSE
carpi_settings-0.1.2.dist-info/METADATA
carpi_settings-0.1.2.dist-info/WHEEL
carpi_settings-0.1.2.dist-info/top_level.txt
carpi_settings-0.1.2.dist-info/RECORD
