Metadata-Version: 2.1
Name: carpi-settings
Version: 0.1.2
Summary: A library providing utilities for storing settings in a CarPi application.
Home-page: https://github.com/rGunti/CarPi-Settings
Author: Raphael "rGunti" Guntersweiler
Author-email: raphael@rgunti.ch
License: MIT
Keywords: carpi app settings
Platform: UNKNOWN
Classifier: Development Status :: 3 - Alpha
Classifier: License :: OSI Approved :: MIT License
Classifier: Programming Language :: Python :: 3.6
Requires-Dist: carpi-commons
Requires-Dist: wheel
Provides-Extra: redis
Requires-Dist: redis ; extra == 'redis'
